nutils_poly-1.0.1.dist-info/METADATA
nutils_poly-1.0.1.dist-info/WHEEL
nutils_poly.libs/libgcc_s-1e52349c.so.1
nutils_poly/__init__.py
nutils_poly/nutils_poly.abi3.so
nutils_poly-1.0.1.dist-info/RECORD
