Metadata-Version: 2.3
Name: nutils-poly
Version: 1.0.1
Classifier: Programming Language :: Rust
Classifier: Programming Language :: Python :: Implementation :: CPython
Classifier: Programming Language :: Python :: Implementation :: PyPy
Requires-Dist: numpy
Summary: Low-level functions for evaluating and manipulating polynomials (Python bindings)
Author: Evalf <info@evalf.com>
Author-email: Evalf <info@evalf.com>
License: MIT
Requires-Python: >=3.8
Project-URL: repository, https://github.com/nutils/poly-py
